LICENSE.txt
MANIFEST.in
README.md
VERSION.txt
pyproject.toml
src/vzg.jconv.egg-info/PKG-INFO
src/vzg.jconv.egg-info/SOURCES.txt
src/vzg.jconv.egg-info/dependency_links.txt
src/vzg.jconv.egg-info/entry_points.txt
src/vzg.jconv.egg-info/requires.txt
src/vzg.jconv.egg-info/top_level.txt
src/vzg/jconv/__init__.py
src/vzg/jconv/errors.py
src/vzg/jconv/gapi.py
src/vzg/jconv/interfaces.py
src/vzg/jconv/archives/__init__.py
src/vzg/jconv/archives/oai.py
src/vzg/jconv/archives/springer.py
src/vzg/jconv/converter/__init__.py
src/vzg/jconv/converter/jats.py
src/vzg/jconv/converter/oai.py
src/vzg/jconv/journal/__init__.py
src/vzg/jconv/langcode/__init__.py
src/vzg/jconv/langcode/language-codes.json
src/vzg/jconv/person/__init__.py
src/vzg/jconv/publisher/__init__.py
src/vzg/jconv/publisher/publisher-codes.json
src/vzg/jconv/schema/article_schema.json
src/vzg/jconv/test/__init__.py
src/vzg/jconv/test/conftest.py
src/vzg/jconv/test/test_archives.py
src/vzg/jconv/test/test_jats_article.py
src/vzg/jconv/test/test_jats_converter.py
src/vzg/jconv/test/test_jats_degruyter.py
src/vzg/jconv/test/test_jatsdate.py
src/vzg/jconv/test/test_journal.py
src/vzg/jconv/test/test_langcode.py
src/vzg/jconv/test/test_oai_article.py
src/vzg/jconv/test/test_oai_converter.py
src/vzg/jconv/test/test_person.py
src/vzg/jconv/test/test_publisher.py
src/vzg/jconv/tools/__init__.py
src/vzg/jconv/tools/simple_conv.py
src/vzg/jconv/utils/__init__.py
src/vzg/jconv/utils/date.py