Metadata-Version: 2.4
Name: vzg.jconv
Version: 1.5.0
Summary: Create articles (articelformat) from various sources
Author-email: "Marc-J. Tegethoff" <tegethoff@gbv.de>
License: GNU Affero General Public License v3
Project-URL: PyPI, https://pypi.python.org/pypi/vzg.jconv
Project-URL: Source, https://github.com/gbv/vzg.jconv
Project-URL: Tracker, https://github.com/gbv/vzg.jconv/issues
Keywords: VZG,Python,JSON,XML,JAST
Classifier: Intended Audience :: Developers
Classifier: Programming Language :: Python
Classifier: Programming Language :: Python :: 3.12
Classifier: Programming Language :: Python :: 3.13
Classifier: Programming Language :: Python :: 3.14
Classifier: Operating System :: OS Independent
Classifier: License :: OSI Approved :: GNU Affero General Public License v3
Requires-Python: >=3.12
License-File: LICENSE.txt
Requires-Dist: jsonschema
Requires-Dist: lxml
Requires-Dist: setuptools
Requires-Dist: wheel
Requires-Dist: zope.interface
Dynamic: license-file
